mydupfilekiller/console.py
mydupfilekiller/core.py
mydupfilekiller/exceptions.py
mydupfilekiller/gui.py
mydupfilekiller/wx_gui.xrc
mydupfilekiller/__init__.py
mydupfilekiller-2.5.dist-info/DESCRIPTION.rst
mydupfilekiller-2.5.dist-info/entry_points.txt
mydupfilekiller-2.5.dist-info/METADATA
mydupfilekiller-2.5.dist-info/metadata.json
mydupfilekiller-2.5.dist-info/RECORD
mydupfilekiller-2.5.dist-info/top_level.txt
mydupfilekiller-2.5.dist-info/WHEEL
