Metadata-Version: 2.0
Name: mydupfilekiller
Version: 2.5
Summary: A Duplicate File Killer
Home-page: https://github.com/wiadufachen/mydupfilekiller
Author: Wiadufa Chen
Author-email: wiadufachen@gmail.com
License: UNKNOWN
Platform: UNKNOWN
Classifier: Programming Language :: Python
Classifier: Programming Language :: Python :: 3
Classifier: License :: OSI Approved :: Apache Software License
Classifier: Development Status :: 4 - Beta
Classifier: Operating System :: OS Independent
Requires-Dist: argparse
Requires-Dist: cython
